ai_client/__init__.py
ai_client/base_client.py
ai_client/claude_client.py
ai_client/cohere_client.py
ai_client/deepseek_client.py
ai_client/gemini_client.py
ai_client/mistral_client.py
ai_client/openai_client.py
ai_client/pricing.json
ai_client/pricing.py
ai_client/qwen_client.py
ai_client/response.py
ai_client/utils.py
generic_llm_api_client-0.3.2.dist-info/licenses/LICENSE
generic_llm_api_client-0.3.2.dist-info/METADATA
generic_llm_api_client-0.3.2.dist-info/WHEEL
generic_llm_api_client-0.3.2.dist-info/top_level.txt
generic_llm_api_client-0.3.2.dist-info/RECORD
