Metadata-Version: 2.4
Name: generic-llm-api-client
Version: 0.3.2
Summary: A unified, provider-agnostic Python client for multiple LLM APIs
Author-email: Sorin Marti <sorin.marti@gmail.com>
Maintainer-email: Sorin Marti <sorin.marti@gmail.com>
License: MIT
Project-URL: Homepage, https://github.com/RISE-UNIBAS/generic_llm_api_client
Project-URL: Documentation, https://github.com/RISE-UNIBAS/generic_llm_api_client#readme
Project-URL: Repository, https://github.com/RISE-UNIBAS/generic_llm_api_client
Project-URL: Issues, https://github.com/RISE-UNIBAS/generic_llm_api_client/issues
Keywords: llm,ai,openai,anthropic,claude,gemini,mistral,deepseek,qwen,cohere,api-client,humanities,research,benchmarking
Classifier: Development Status :: 3 - Alpha
Classifier: Intended Audience :: Developers
Classifier: Intended Audience :: Science/Research
Classifier: License :: OSI Approved :: MIT License
Classifier: Programming Language :: Python :: 3
Classifier: Programming Language :: Python :: 3.9
Classifier: Programming Language :: Python :: 3.10
Classifier: Programming Language :: Python :: 3.11
Classifier: Programming Language :: Python :: 3.12
Classifier: Topic :: Scientific/Engineering :: Artificial Intelligence
Classifier: Topic :: Software Development :: Libraries :: Python Modules
Requires-Python: >=3.9
License-File: LICENSE
Requires-Dist: anthropic~=0.71.0
Requires-Dist: openai~=2.6.1
Requires-Dist: mistralai~=1.9.11
Requires-Dist: google-genai~=1.46.0
Requires-Dist: cohere~=5.20.0
Requires-Dist: requests~=2.32.5
Provides-Extra: dev
Requires-Dist: pytest>=7.0.0; extra == "dev"
Requires-Dist: pytest-asyncio>=0.21.0; extra == "dev"
Requires-Dist: pytest-cov>=4.0.0; extra == "dev"
Requires-Dist: pytest-mock>=3.10.0; extra == "dev"
Requires-Dist: python-dotenv>=1.0.0; extra == "dev"
Requires-Dist: Pillow>=10.0.0; extra == "dev"
Requires-Dist: black>=23.0.0; extra == "dev"
Requires-Dist: mypy>=1.0.0; extra == "dev"
Requires-Dist: ruff>=0.1.0; extra == "dev"
Provides-Extra: test
Requires-Dist: pytest>=7.0.0; extra == "test"
Requires-Dist: pytest-asyncio>=0.21.0; extra == "test"
Requires-Dist: pytest-cov>=4.0.0; extra == "test"
Requires-Dist: pytest-mock>=3.10.0; extra == "test"
Requires-Dist: python-dotenv>=1.0.0; extra == "test"
Requires-Dist: Pillow>=10.0.0; extra == "test"
Dynamic: license-file
